{
  "matchInfo": {
    "id": "9webi0w8dceyc4mudjlmbj8r8",
    "coverageLevel": "13",
    "date": "2025-10-19Z",
    "time": "23:00:00Z",
    "localDate": "2025-10-19",
    "localTime": "18:00:00",
    "week": "2",
    "postMatch": "1",
    "numberOfPeriods": 2,
    "periodLength": 45,
    "var": "1",
    "lastUpdated": "2025-10-23T16:10:07Z",
    "description": "Libertad vs Universidad Católica",
    "sport": {
      "id": "289u5typ3vp4ifwh5thalohmq",
      "name": "Soccer"
    },
    "ruleset": {
      "id": "79plas4983031idr6vw83nuel",
      "name": "Men"
    },
    "competition": {
      "id": "6lwpjhktjhl9g7x2w7njmzva6",
      "name": "Liga Pro",
      "knownName": "Ecuador Liga Pro",
      "sponsorName": "LigaPro Ecuabet",
      "competitionCode": "PRO",
      "competitionFormat": "Domestic league",
      "country": {
        "id": "6pyj2bytt2osbjk69owzfehcg",
        "name": "Ecuador"
      }
    },
    "tournamentCalendar": {
      "id": "5kew94t602zbzw5zv2rjkcetw",
      "startDate": "2025-02-15Z",
      "endDate": "2025-12-21Z",
      "name": "2025"
    },
    "stage": {
      "id": "6gwd6sm0cebqgnpqvg6io83ys",
      "formatId": "c7zluzt2rr4oxoc7xslnnfzkl",
      "startDate": "2025-10-05Z",
      "endDate": "2025-12-21Z",
      "name": "Championship Round"
    },
    "contestant": [
      {
        "id": "37k9jifjhdcnb31yzzkmo7uhg",
        "name": "Libertad",
        "shortName": "Libertad",
        "officialName": "Libertad Fútbol Club",
        "code": "LIB",
        "position": "home",
        "country": {
          "id": "6pyj2bytt2osbjk69owzfehcg",
          "name": "Ecuador"
        }
      },
      {
        "id": "85tqel61vdk8sfz1vsb1jykk7",
        "name": "Universidad Católica",
        "shortName": "U. Católica",
        "officialName": "CD Universidad Católica del Ecuador",
        "code": "UCA",
        "position": "away",
        "country": {
          "id": "6pyj2bytt2osbjk69owzfehcg",
          "name": "Ecuador"
        }
      }
    ],
    "venue": {
      "id": "3nxzt141fyvp6ms17ijicdi91",
      "neutral": "no",
      "longName": "Estadio Federativo Reina del Cisne",
      "shortName": "Estadio Federativo Reina del Cisne",
      "latitude": "-3.992013134",
      "longitude": "-79.207735062"
    }
  },
  "liveData": {
    "matchDetails": {
      "periodId": 14,
      "matchStatus": "Played",
      "winner": "draw",
      "matchLengthMin": 99,
      "matchLengthSec": 12,
      "period": [
        {
          "id": 1,
          "start": "2025-10-19T23:00:24Z",
          "end": "2025-10-19T23:48:29Z",
          "lengthMin": 48,
          "lengthSec": 5,
          "announcedInjuryTime": 180
        },
        {
          "id": 2,
          "start": "2025-10-20T00:07:15Z",
          "end": "2025-10-20T00:58:22Z",
          "lengthMin": 51,
          "lengthSec": 7,
          "announcedInjuryTime": 360
        }
      ],
      "scores": {
        "ht": {
          "home": 1,
          "away": 0
        },
        "ft": {
          "home": 1,
          "away": 1
        },
        "total": {
          "home": 1,
          "away": 1
        }
      }
    },
    "goal": [
      {
        "contestantId": "37k9jifjhdcnb31yzzkmo7uhg",
        "periodId": 1,
        "timeMin": 23,
        "timeMinSec": "22:32",
        "lastUpdated": "2025-10-19T23:24:10Z",
        "timestamp": "2025-10-19T23:22:57Z",
        "type": "G",
        "scorerId": "677337y7ae2lsr9tvlaaxcfyt",
        "scorerName": "C. Arboleda",
        "assistPlayerId": "5w31tnx3x1093n9mojsbjo9p0",
        "assistPlayerName": "Y. Quiñónez",
        "optaEventId": "2861797651",
        "homeScore": 1,
        "awayScore": 0
      },
      {
        "contestantId": "85tqel61vdk8sfz1vsb1jykk7",
        "periodId": 2,
        "timeMin": 82,
        "timeMinSec": "81:25",
        "lastUpdated": "2025-10-20T00:44:16Z",
        "timestamp": "2025-10-20T00:43:41Z",
        "type": "PG",
        "scorerId": "ecd9ao2y87pqxws6040ipn7dg",
        "scorerName": "A. Londoño",
        "optaEventId": "2861818945",
        "homeScore": 1,
        "awayScore": 1
      }
    ],
    "card": [
      {
        "contestantId": "85tqel61vdk8sfz1vsb1jykk7",
        "periodId": 1,
        "timeMin": 36,
        "timeMinSec": "35:12",
        "lastUpdated": "2025-10-19T23:35:45Z",
        "timestamp": "2025-10-19T23:35:36Z",
        "type": "YC",
        "playerId": "dp2tnjilpke1ph1fdjgno9zop",
        "playerName": "E. Mejía",
        "optaEventId": "2861801947",
        "cardReason": "Foul"
      },
      {
        "contestantId": "37k9jifjhdcnb31yzzkmo7uhg",
        "periodId": 1,
        "timeMin": 44,
        "timeMinSec": "43:44",
        "lastUpdated": "2025-10-19T23:44:18Z",
        "timestamp": "2025-10-19T23:44:09Z",
        "type": "YC",
        "playerId": "81l0r066zi9ej72m0cszlsd4a",
        "playerName": "J. Humanante",
        "optaEventId": "2861804493",
        "cardReason": "Foul"
      },
      {
        "contestantId": "37k9jifjhdcnb31yzzkmo7uhg",
        "periodId": 2,
        "timeMin": 55,
        "timeMinSec": "54:05",
        "lastUpdated": "2025-10-20T00:16:30Z",
        "timestamp": "2025-10-20T00:16:21Z",
        "type": "YC",
        "playerId": "cuuv2aodsmm9chk100fe0ffmd",
        "playerName": "E. Caicedo",
        "optaEventId": "2861811973",
        "cardReason": "Foul"
      },
      {
        "contestantId": "37k9jifjhdcnb31yzzkmo7uhg",
        "periodId": 2,
        "timeMin": 68,
        "timeMinSec": "67:44",
        "lastUpdated": "2025-10-20T00:30:07Z",
        "timestamp": "2025-10-20T00:30:00Z",
        "type": "YC",
        "playerId": "64sy42d3620qjkc6kbxhm4pn9",
        "playerName": "O. Quiñónez",
        "optaEventId": "2861815305",
        "cardReason": "Not Retreating"
      },
      {
        "contestantId": "85tqel61vdk8sfz1vsb1jykk7",
        "periodId": 2,
        "timeMin": 68,
        "timeMinSec": "67:50",
        "lastUpdated": "2025-10-20T00:31:13Z",
        "timestamp": "2025-10-20T00:30:06Z",
        "type": "YC",
        "playerId": "dbzannb5pw72n5t4sbotswhuy",
        "playerName": "E. Clavijo",
        "optaEventId": "2861815491",
        "cardReason": "Dissent"
      },
      {
        "contestantId": "85tqel61vdk8sfz1vsb1jykk7",
        "periodId": 2,
        "timeMin": 69,
        "timeMinSec": "68:32",
        "lastUpdated": "2025-10-20T00:31:43Z",
        "timestamp": "2025-10-20T00:30:48Z",
        "type": "YC",
        "playerId": "b5b0gp63p5mdpusl6lc56q4bu",
        "playerName": "G. Anangonó",
        "optaEventId": "2861815609",
        "cardReason": "Argument"
      },
      {
        "contestantId": "37k9jifjhdcnb31yzzkmo7uhg",
        "periodId": 2,
        "timeMin": 92,
        "timeMinSec": "91:25",
        "lastUpdated": "2025-10-20T00:53:46Z",
        "timestamp": "2025-10-20T00:53:41Z",
        "type": "YC",
        "playerId": "du0551faegg7ntsvlglx2xomh",
        "playerName": "J. Monaga",
        "optaEventId": "2861821351",
        "cardReason": "Foul"
      },
      {
        "contestantId": "37k9jifjhdcnb31yzzkmo7uhg",
        "periodId": 2,
        "timeMin": 95,
        "timeMinSec": "94:32",
        "lastUpdated": "2025-10-20T00:57:06Z",
        "timestamp": "2025-10-20T00:56:47Z",
        "type": "YC",
        "playerId": "bjzxx0p23kmsxnxvlm9e8ajqi",
        "playerName": "I. Zambrano",
        "optaEventId": "2861821891",
        "cardReason": "Dissent"
      }
    ],
    "substitute": [
      {
        "contestantId": "37k9jifjhdcnb31yzzkmo7uhg",
        "periodId": 2,
        "timeMin": 46,
        "timeMinSec": "45:00",
        "lastUpdated": "2025-10-20T00:07:06Z",
        "timestamp": "2025-10-20T00:07:01Z",
        "playerOnId": "1al0d9v3ldh6hbs73td99fuok",
        "playerOnName": "J. Bravo",
        "playerOffId": "81l0r066zi9ej72m0cszlsd4a",
        "playerOffName": "J. Humanante",
        "subReason": "Tactical"
      },
      {
        "contestantId": "85tqel61vdk8sfz1vsb1jykk7",
        "periodId": 2,
        "timeMin": 61,
        "timeMinSec": "60:38",
        "lastUpdated": "2025-10-20T00:22:59Z",
        "timestamp": "2025-10-20T00:22:54Z",
        "playerOnId": "9ggta4hzy0w4xkukczrti5y7e",
        "playerOnName": "J. Fajardo",
        "playerOffId": "6qdkaa9ae67qy7ipa11a8z17t",
        "playerOffName": "B. Palacios",
        "subReason": "Tactical"
      },
      {
        "contestantId": "37k9jifjhdcnb31yzzkmo7uhg",
        "periodId": 2,
        "timeMin": 72,
        "timeMinSec": "71:22",
        "lastUpdated": "2025-10-20T00:33:44Z",
        "timestamp": "2025-10-20T00:33:37Z",
        "playerOnId": "an1skfibmw4uj0dqr31n9dfro",
        "playerOnName": "N. Caicedo",
        "playerOffId": "cuuv2aodsmm9chk100fe0ffmd",
        "playerOffName": "E. Caicedo",
        "subReason": "Tactical"
      },
      {
        "contestantId": "37k9jifjhdcnb31yzzkmo7uhg",
        "periodId": 2,
        "timeMin": 72,
        "timeMinSec": "71:27",
        "lastUpdated": "2025-10-20T00:35:24Z",
        "timestamp": "2025-10-20T00:33:43Z",
        "playerOnId": "2g9n183x59e764xsohjxzcwes",
        "playerOnName": "A. García",
        "playerOffId": "64sy42d3620qjkc6kbxhm4pn9",
        "playerOffName": "O. Quiñónez",
        "subReason": "Tactical"
      },
      {
        "contestantId": "85tqel61vdk8sfz1vsb1jykk7",
        "periodId": 2,
        "timeMin": 76,
        "timeMinSec": "75:56",
        "lastUpdated": "2025-10-20T00:41:12Z",
        "timestamp": "2025-10-20T00:38:12Z",
        "playerOnId": "ep0zxr95nch7d9gqbb47afg9g",
        "playerOnName": "D. Romero",
        "playerOffId": "4xhrvnq03r13f2bwt0vxm46ol",
        "playerOffName": "M. Alonso",
        "subReason": "Tactical"
      },
      {
        "contestantId": "85tqel61vdk8sfz1vsb1jykk7",
        "periodId": 2,
        "timeMin": 76,
        "timeMinSec": "75:58",
        "lastUpdated": "2025-10-20T00:41:31Z",
        "timestamp": "2025-10-20T00:38:14Z",
        "playerOnId": "dukia9yvlzkug4gw890nwneok",
        "playerOnName": "A. Rodríguez",
        "playerOffId": "b5b0gp63p5mdpusl6lc56q4bu",
        "playerOffName": "G. Anangonó",
        "subReason": "Tactical"
      },
      {
        "contestantId": "37k9jifjhdcnb31yzzkmo7uhg",
        "periodId": 2,
        "timeMin": 83,
        "timeMinSec": "82:01",
        "lastUpdated": "2025-10-20T00:45:50Z",
        "timestamp": "2025-10-20T00:44:17Z",
        "playerOnId": "du0551faegg7ntsvlglx2xomh",
        "playerOnName": "J. Monaga",
        "playerOffId": "677337y7ae2lsr9tvlaaxcfyt",
        "playerOffName": "C. Arboleda",
        "subReason": "Tactical"
      },
      {
        "contestantId": "85tqel61vdk8sfz1vsb1jykk7",
        "periodId": 2,
        "timeMin": 89,
        "timeMinSec": "88:48",
        "lastUpdated": "2025-10-20T00:53:07Z",
        "timestamp": "2025-10-20T00:51:03Z",
        "playerOnId": "2uwx5yky9qc644tztx2zti28l",
        "playerOnName": "F. Martínez",
        "playerOffId": "d5hgq9en54sht3iy363fe2imt",
        "playerOffName": "M. Díaz",
        "subReason": "Tactical"
      },
      {
        "contestantId": "37k9jifjhdcnb31yzzkmo7uhg",
        "periodId": 2,
        "timeMin": 89,
        "timeMinSec": "88:50",
        "lastUpdated": "2025-10-20T00:51:16Z",
        "timestamp": "2025-10-20T00:51:06Z",
        "playerOnId": "94zl13qqc4skq36oq8t6ww0h6",
        "playerOnName": "Á. Quiñónez",
        "playerOffId": "5rps6forynpfjmqlijt0fgpn9",
        "playerOffName": "W. Ayoví",
        "subReason": "Tactical"
      },
      {
        "contestantId": "85tqel61vdk8sfz1vsb1jykk7",
        "periodId": 2,
        "timeMin": 89,
        "timeMinSec": "88:57",
        "lastUpdated": "2025-10-20T00:53:19Z",
        "timestamp": "2025-10-20T00:51:13Z",
        "playerOnId": "eb2d87d8tfi6cxjcntkfdrdhw",
        "playerOnName": "L. Moreno",
        "playerOffId": "7f1eclcdjezvwn0vg4bm4muzu",
        "playerOffName": "J. Cacciabue",
        "subReason": "Tactical"
      }
    ],
    "VAR": [
      {
        "contestantId": "85tqel61vdk8sfz1vsb1jykk7",
        "periodId": 2,
        "timeMin": 80,
        "timeMinSec": "79:14",
        "lastUpdated": "2025-10-20T00:41:49Z",
        "timestamp": "2025-10-20T00:41:30Z",
        "type": "Penalty not awarded",
        "decision": "Cancelled",
        "outcome": "Penalty",
        "playerId": "9ggta4hzy0w4xkukczrti5y7e",
        "playerName": "J. Fajardo",
        "optaEventId": "2861818423"
      }
    ],
    "lineUp": [
      {
        "contestantId": "37k9jifjhdcnb31yzzkmo7uhg",
        "formationUsed": "442",
        "player": [
          {
            "playerId": "cdbm6p6o72a5cgycoleoe7ok4",
            "firstName": "Felix Jostyn",
            "lastName": "Mina Caicedo",
            "shortFirstName": "Jostyn",
            "shortLastName": "Mina",
            "matchName": "F. Mina",
            "shirtNumber": 12,
            "position": "Goalkeeper",
            "positionSide": "Centre",
            "formationPlace": "1",
            "stat": [
              {
                "type": "accuratePass",
                "value": "18"
              },
              {
                "type": "gameStarted",
                "value": "1"
              },
              {
                "type": "goalKicks",
                "value": "13"
              },
              {
                "type": "goalsConceded",
                "value": "1"
              },
              {
                "type": "minsPlayed",
                "value": "90"
              },
              {
                "type": "penGoalsConceded",
                "value": "1"
              },
              {
                "type": "penaltyFaced",
                "value": "1"
              },
              {
                "type": "saves",
                "value": "4"
              },
              {
                "type": "totalClearance",
                "value": "1"
              },
              {
                "type": "totalPass",
                "value": "33"
              },
              {
                "type": "wasFouled",
                "value": "1"
              },
              {
                "type": "formationPlace",
                "value": "1"
              }
            ]
          },
          {
            "playerId": "64sy42d3620qjkc6kbxhm4pn9",
            "firstName": "Orlín Peter",
            "lastName": "Quiñónez Ayoví",
            "shortFirstName": "Orlin",
            "shortLastName": "Quiñónez",
            "knownName": "Orlin Quiñónez",
            "matchName": "O. Quiñónez",
            "shirtNumber": 6,
            "position": "Defender",
            "positionSide": "Left",
            "formationPlace": "3",
            "stat": [
              {
                "type": "accuratePass",
                "value": "12"
              },
              {
                "type": "gameStarted",
                "value": "1"
              },
              {
                "type": "minsPlayed",
                "value": "72"
              },
              {
                "type": "totalClearance",
                "value": "3"
              },
              {
                "type": "totalPass",
                "value": "15"
              },
              {
                "type": "totalSubOff",
                "value": "1"
              },
              {
                "type": "totalTackle",
                "value": "1"
              },
              {
                "type": "totalThrows",
                "value": "10"
              },
              {
                "type": "wonTackle",
                "value": "1"
              },
              {
                "type": "yellowCard",
                "value": "1"
              },
              {
                "type": "formationPlace",
                "value": "3"
              }
            ]
          },
          {
            "playerId": "b8qxh19f35zt4w7evx6ozrn55",
            "firstName": "Kevin Steeven",
            "lastName": "Becerra Wila",
            "shortFirstName": "Kevin",
            "shortLastName": "Becerra",
            "matchName": "K. Becerra",
            "shirtNumber": 3,
            "position": "Defender",
            "positionSide": "Left/Centre",
            "formationPlace": "6",
            "stat": [
              {
                "type": "accuratePass",
                "value": "17"
              },
              {
                "type": "gameStarted",
                "value": "1"
              },
              {
                "type": "goalsConceded",
                "value": "1"
              },
              {
                "type": "minsPlayed",
                "value": "90"
              },
              {
                "type": "penGoalsConceded",
                "value": "1"
              },
              {
                "type": "totalClearance",
                "value": "5"
              },
              {
                "type": "totalPass",
                "value": "25"
              },
              {
                "type": "formationPlace",
                "value": "6"
              }
            ]
          },
          {
            "playerId": "t8h2eun8lgejiarkex4y1ht6",
            "firstName": "Ronny Alfonso",
            "lastName": "Biojó Preciado",
            "shortFirstName": "Ronny",
            "shortLastName": "Biojó",
            "matchName": "R. Biojó",
            "shirtNumber": 4,
            "position": "Defender",
            "positionSide": "Centre/Right",
            "formationPlace": "5",
            "stat": [
              {
                "type": "accuratePass",
                "value": "18"
              },
              {
                "type": "fouls",
                "value": "1"
              },
              {
                "type": "gameStarted",
                "value": "1"
              },
              {
                "type": "goalsConceded",
                "value": "1"
              },
              {
                "type": "lostCorners",
                "value": "2"
              },
              {
                "type": "minsPlayed",
                "value": "90"
              },
              {
                "type": "penGoalsConceded",
                "value": "1"
              },
              {
                "type": "penaltyConceded",
                "value": "1"
              },
              {
                "type": "shotOffTarget",
                "value": "1"
              },
              {
                "type": "totalClearance",
                "value": "6"
              },
              {
                "type": "totalPass",
                "value": "22"
              },
              {
                "type": "totalScoringAtt",
                "value": "1"
              },
              {
                "type": "totalTackle",
                "value": "1"
              },
              {
                "type": "wasFouled",
                "value": "2"
              },
              {
                "type": "wonTackle",
                "value": "1"
              },
              {
                "type": "formationPlace",
                "value": "5"
              }
            ]
          },
          {
            "playerId": "e9dx4jgloxfmi6zi1domqfzai",
            "firstName": "Jimmy Denilson",
            "lastName": "Bolaños Cervantes",
            "shortFirstName": "Denilson",
            "shortLastName": "Bolaños",
            "matchName": "D. Bolaños",
            "shirtNumber": 25,
            "position": "Defender",
            "positionSide": "Right",
            "formationPlace": "2",
            "stat": [
              {
                "type": "accuratePass",
                "value": "11"
              },
              {
                "type": "gameStarted",
                "value": "1"
              },
              {
                "type": "goalsConceded",
                "value": "1"
              },
              {
                "type": "lostCorners",
                "value": "1"
              },
              {
                "type": "minsPlayed",
                "value": "90"
              },
              {
                "type": "penGoalsConceded",
                "value": "1"
              },
              {
                "type": "totalClearance",
                "value": "5"
              },
              {
                "type": "totalPass",
                "value": "17"
              },
              {
                "type": "totalTackle",
                "value": "2"
              },
              {
                "type": "totalThrows",
                "value": "5"
              },
              {
                "type": "wonCorners",
                "value": "1"
              },
              {
                "type": "wonTackle",
                "value": "2"
              },
              {
                "type": "formationPlace",
                "value": "2"
              }
            ]
          },
          {
            "playerId": "677337y7ae2lsr9tvlaaxcfyt",
            "firstName": "Carlos Alexi",
            "lastName": "Arboleda Ruiz",
            "shortFirstName": "Carlos",
            "shortLastName": "Arboleda",
            "matchName": "C. Arboleda",
            "shirtNumber": 37,
            "position": "Midfielder",
            "positionSide": "Left",
            "formationPlace": "11",
            "stat": [
              {
                "type": "accuratePass",
                "value": "11"
              },
              {
                "type": "gameStarted",
                "value": "1"
              },
              {
                "type": "goals",
                "value": "1"
              },
              {
                "type": "goalsConceded",
                "value": "1"
              },
              {
                "type": "minsPlayed",
                "value": "83"
              },
              {
                "type": "ontargetScoringAtt",
                "value": "2"
              },
              {
                "type": "penGoalsConceded",
                "value": "1"
              },
              {
                "type": "totalPass",
                "value": "19"
              },
              {
                "type": "totalScoringAtt",
                "value": "2"
              },
              {
                "type": "totalSubOff",
                "value": "1"
              },
              {
                "type": "totalTackle",
                "value": "5"
              },
              {
                "type": "wasFouled",
                "value": "2"
              },
              {
                "type": "wonTackle",
                "value": "4"
              },
              {
                "type": "formationPlace",
                "value": "11"
              }
            ]
          },
          {
            "playerId": "bjzxx0p23kmsxnxvlm9e8ajqi",
            "firstName": "Iván Frangoy",
            "lastName": "Zambrano Vera",
            "shortFirstName": "Iván",
            "shortLastName": "Zambrano",
            "matchName": "I. Zambrano",
            "shirtNumber": 7,
            "position": "Midfielder",
            "positionSide": "Left/Centre",
            "formationPlace": "8",
            "captain": "yes",
            "stat": [
              {
                "type": "accuratePass",
                "value": "17"
              },
              {
                "type": "blockedScoringAtt",
                "value": "1"
              },
              {
                "type": "gameStarted",
                "value": "1"
              },
              {
                "type": "goalsConceded",
                "value": "1"
              },
              {
                "type": "minsPlayed",
                "value": "90"
              },
              {
                "type": "ontargetScoringAtt",
                "value": "1"
              },
              {
                "type": "penGoalsConceded",
                "value": "1"
              },
              {
                "type": "shotOffTarget",
                "value": "1"
              },
              {
                "type": "totalClearance",
                "value": "2"
              },
              {
                "type": "totalPass",
                "value": "28"
              },
              {
                "type": "totalScoringAtt",
                "value": "3"
              },
              {
                "type": "totalTackle",
                "value": "4"
              },
              {
                "type": "wonTackle",
                "value": "3"
              },
              {
                "type": "yellowCard",
                "value": "1"
              },
              {
                "type": "formationPlace",
                "value": "8"
              }
            ]
          },
          {
            "playerId": "81l0r066zi9ej72m0cszlsd4a",
            "firstName": "Jean Carlos",
            "lastName": "Humanante Vargas",
            "shortFirstName": "Jean",
            "shortLastName": "Humanante",
            "matchName": "J. Humanante",
            "shirtNumber": 50,
            "position": "Midfielder",
            "positionSide": "Centre/Right",
            "formationPlace": "4",
            "stat": [
              {
                "type": "accuratePass",
                "value": "11"
              },
              {
                "type": "blockedScoringAtt",
                "value": "3"
              },
              {
                "type": "fouls",
                "value": "1"
              },
              {
                "type": "gameStarted",
                "value": "1"
              },
              {
                "type": "minsPlayed",
                "value": "45"
              },
              {
                "type": "shotOffTarget",
                "value": "1"
              },
              {
                "type": "totalPass",
                "value": "16"
              },
              {
                "type": "totalScoringAtt",
                "value": "4"
              },
              {
                "type": "totalSubOff",
                "value": "1"
              },
              {
                "type": "totalTackle",
                "value": "1"
              },
              {
                "type": "yellowCard",
                "value": "1"
              },
              {
                "type": "formationPlace",
                "value": "4"
              }
            ]
          },
          {
            "playerId": "5w31tnx3x1093n9mojsbjo9p0",
            "firstName": "Yerlin Josué",
            "lastName": "Quiñónez Nazareno",
            "shortFirstName": "Yerlin",
            "shortLastName": "Quiñónez",
            "knownName": "Yerlin Quiñónez",
            "matchName": "Y. Quiñónez",
            "shirtNumber": 70,
            "position": "Midfielder",
            "positionSide": "Right",
            "formationPlace": "7",
            "stat": [
              {
                "type": "accuratePass",
                "value": "8"
              },
              {
                "type": "fouls",
                "value": "2"
              },
              {
                "type": "gameStarted",
                "value": "1"
              },
              {
                "type": "goalAssist",
                "value": "1"
              },
              {
                "type": "goalsConceded",
                "value": "1"
              },
              {
                "type": "lostCorners",
                "value": "1"
              },
              {
                "type": "minsPlayed",
                "value": "90"
              },
              {
                "type": "ontargetScoringAtt",
                "value": "1"
              },
              {
                "type": "penGoalsConceded",
                "value": "1"
              },
              {
                "type": "totalClearance",
                "value": "1"
              },
              {
                "type": "totalOffside",
                "value": "1"
              },
              {
                "type": "totalPass",
                "value": "15"
              },
              {
                "type": "totalScoringAtt",
                "value": "1"
              },
              {
                "type": "totalTackle",
                "value": "1"
              },
              {
                "type": "wonTackle",
                "value": "1"
              },
              {
                "type": "formationPlace",
                "value": "7"
              }
            ]
          },
          {
            "playerId": "cuuv2aodsmm9chk100fe0ffmd",
            "firstName": "Eber Edison",
            "lastName": "Caicedo Peralta",
            "shortFirstName": "Eber",
            "shortLastName": "Caicedo",
            "knownName": "Eber Caicedo",
            "matchName": "E. Caicedo",
            "shirtNumber": 19,
            "position": "Striker",
            "positionSide": "Left/Centre",
            "formationPlace": "9",
            "stat": [
              {
                "type": "accuratePass",
                "value": "7"
              },
              {
                "type": "fouls",
                "value": "2"
              },
              {
                "type": "gameStarted",
                "value": "1"
              },
              {
                "type": "minsPlayed",
                "value": "72"
              },
              {
                "type": "shotOffTarget",
                "value": "1"
              },
              {
                "type": "totalClearance",
                "value": "1"
              },
              {
                "type": "totalPass",
                "value": "17"
              },
              {
                "type": "totalScoringAtt",
                "value": "1"
              },
              {
                "type": "totalSubOff",
                "value": "1"
              },
              {
                "type": "wasFouled",
                "value": "1"
              },
              {
                "type": "yellowCard",
                "value": "1"
              },
              {
                "type": "formationPlace",
                "value": "9"
              }
            ]
          },
          {
            "playerId": "5rps6forynpfjmqlijt0fgpn9",
            "firstName": "Wilter Andrés",
            "lastName": "Ayoví Mina",
            "shortFirstName": "Wilter",
            "shortLastName": "Ayoví",
            "matchName": "W. Ayoví",
            "shirtNumber": 8,
            "position": "Striker",
            "positionSide": "Centre/Right",
            "formationPlace": "10",
            "stat": [
              {
                "type": "accuratePass",
                "value": "14"
              },
              {
                "type": "cornerTaken",
                "value": "1"
              },
              {
                "type": "fouls",
                "value": "1"
              },
              {
                "type": "gameStarted",
                "value": "1"
              },
              {
                "type": "goalsConceded",
                "value": "1"
              },
              {
                "type": "minsPlayed",
                "value": "89"
              },
              {
                "type": "ontargetScoringAtt",
                "value": "1"
              },
              {
                "type": "penGoalsConceded",
                "value": "1"
              },
              {
                "type": "totalOffside",
                "value": "1"
              },
              {
                "type": "totalPass",
                "value": "16"
              },
              {
                "type": "totalScoringAtt",
                "value": "1"
              },
              {
                "type": "totalSubOff",
                "value": "1"
              },
              {
                "type": "totalTackle",
                "value": "1"
              },
              {
                "type": "wasFouled",
                "value": "3"
              },
              {
                "type": "wonTackle",
                "value": "1"
              },
              {
                "type": "formationPlace",
                "value": "10"
              }
            ]
          },
          {
            "playerId": "1al0d9v3ldh6hbs73td99fuok",
            "firstName": "Yery Jostin",
            "lastName": "Bravo Gurumendi",
            "shortFirstName": "Jostin",
            "shortLastName": "Bravo",
            "matchName": "J. Bravo",
            "shirtNumber": 30,
            "position": "Substitute",
            "subPosition": "Midfielder",
            "stat": [
              {
                "type": "accuratePass",
                "value": "10"
              },
              {
                "type": "goalsConceded",
                "value": "1"
              },
              {
                "type": "minsPlayed",
                "value": "45"
              },
              {
                "type": "penGoalsConceded",
                "value": "1"
              },
              {
                "type": "totalClearance",
                "value": "1"
              },
              {
                "type": "totalPass",
                "value": "12"
              },
              {
                "type": "totalSubOn",
                "value": "1"
              },
              {
                "type": "totalTackle",
                "value": "1"
              },
              {
                "type": "wasFouled",
                "value": "1"
              },
              {
                "type": "wonTackle",
                "value": "1"
              },
              {
                "type": "formationPlace",
                "value": "0"
              }
            ]
          },
          {
            "playerId": "esrdy1ms5ugjhn1upuyh4dono",
            "firstName": "Sander Antonio",
            "lastName": "Bueno Quiñónez",
            "shortFirstName": "Sander",
            "shortLastName": "Bueno",
            "matchName": "S. Bueno",
            "shirtNumber": 55,
            "position": "Substitute",
            "subPosition": "Midfielder",
            "stat": [
              {
                "type": "formationPlace",
                "value": "0"
              }
            ]
          },
          {
            "playerId": "an1skfibmw4uj0dqr31n9dfro",
            "firstName": "Nestor David",
            "lastName": "Caicedo Mina",
            "shortFirstName": "Nestor",
            "shortLastName": "Caicedo",
            "knownName": "Nestor Caicedo",
            "matchName": "N. Caicedo",
            "shirtNumber": 14,
            "position": "Substitute",
            "subPosition": "Attacker",
            "stat": [
              {
                "type": "accuratePass",
                "value": "1"
              },
              {
                "type": "goalsConceded",
                "value": "1"
              },
              {
                "type": "lostCorners",
                "value": "1"
              },
              {
                "type": "minsPlayed",
                "value": "18"
              },
              {
                "type": "penGoalsConceded",
                "value": "1"
              },
              {
                "type": "totalPass",
                "value": "2"
              },
              {
                "type": "totalSubOn",
                "value": "1"
              },
              {
                "type": "formationPlace",
                "value": "0"
              }
            ]
          },
          {
            "playerId": "9pf86tk4zel6r1skqs620za50",
            "firstName": "Emerson Samuel",
            "lastName": "Castillo Ortíz",
            "shortFirstName": "Samuel",
            "shortLastName": "Castillo",
            "matchName": "S. Castillo",
            "shirtNumber": 99,
            "position": "Substitute",
            "subPosition": "Goalkeeper",
            "stat": [
              {
                "type": "formationPlace",
                "value": "0"
              }
            ]
          },
          {
            "playerId": "2g9n183x59e764xsohjxzcwes",
            "firstName": "Alan Ariel",
            "lastName": "García Jama",
            "shortFirstName": "Alan",
            "shortLastName": "García",
            "matchName": "A. García",
            "shirtNumber": 36,
            "position": "Substitute",
            "subPosition": "Defender",
            "stat": [
              {
                "type": "accuratePass",
                "value": "1"
              },
              {
                "type": "goalsConceded",
                "value": "1"
              },
              {
                "type": "minsPlayed",
                "value": "18"
              },
              {
                "type": "penGoalsConceded",
                "value": "1"
              },
              {
                "type": "totalClearance",
                "value": "1"
              },
              {
                "type": "totalPass",
                "value": "3"
              },
              {
                "type": "totalSubOn",
                "value": "1"
              },
              {
                "type": "formationPlace",
                "value": "0"
              }
            ]
          },
          {
            "playerId": "6llzouvdgu8fzk40lpidjbeok",
            "firstName": "Carlos Jair",
            "lastName": "Gruezo Chamorro",
            "shortFirstName": "Carlos",
            "shortLastName": "Gruezo",
            "matchName": "C. Gruezo",
            "shirtNumber": 23,
            "position": "Substitute",
            "subPosition": "Midfielder",
            "stat": [
              {
                "type": "formationPlace",
                "value": "0"
              }
            ]
          },
          {
            "playerId": "du0551faegg7ntsvlglx2xomh",
            "firstName": "José Luis",
            "lastName": "Monaga Quiñónez",
            "shortFirstName": "José",
            "shortLastName": "Monaga",
            "matchName": "J. Monaga",
            "shirtNumber": 24,
            "position": "Substitute",
            "subPosition": "Defender",
            "stat": [
              {
                "type": "accuratePass",
                "value": "5"
              },
              {
                "type": "fouls",
                "value": "1"
              },
              {
                "type": "lostCorners",
                "value": "1"
              },
              {
                "type": "minsPlayed",
                "value": "7"
              },
              {
                "type": "totalClearance",
                "value": "1"
              },
              {
                "type": "totalPass",
                "value": "6"
              },
              {
                "type": "totalSubOn",
                "value": "1"
              },
              {
                "type": "yellowCard",
                "value": "1"
              },
              {
                "type": "formationPlace",
                "value": "0"
              }
            ]
          },
          {
            "playerId": "e6ki3cyjkjrd0vquc2859nx79",
            "firstName": "Leonel Romario",
            "lastName": "Nazareno Delgado",
            "shortFirstName": "Leonel",
            "shortLastName": "Nazareno",
            "knownName": "Leonel Nazareno",
            "matchName": "L. Nazareno",
            "shirtNumber": 45,
            "position": "Substitute",
            "subPosition": "Goalkeeper",
            "stat": [
              {
                "type": "formationPlace",
                "value": "0"
              }
            ]
          },
          {
            "playerId": "7tlvr6jbte4l8gag516dvlixg",
            "firstName": "Bruno Vidal",
            "lastName": "Pachito Zapatier",
            "shortFirstName": "Bruno",
            "shortLastName": "Pachito",
            "matchName": "B. Pachito",
            "shirtNumber": 80,
            "position": "Substitute",
            "subPosition": "Attacker",
            "stat": [
              {
                "type": "formationPlace",
                "value": "0"
              }
            ]
          },
          {
            "playerId": "94zl13qqc4skq36oq8t6ww0h6",
            "firstName": "Ángel Fernando",
            "lastName": "Quiñónez Guerrero",
            "shortFirstName": "Ángel",
            "shortLastName": "Quiñónez",
            "knownName": "Ángel Quiñónez",
            "matchName": "Á. Quiñónez",
            "shirtNumber": 21,
            "position": "Substitute",
            "subPosition": "Attacker",
            "stat": [
              {
                "type": "accuratePass",
                "value": "2"
              },
              {
                "type": "minsPlayed",
                "value": "1"
              },
              {
                "type": "totalPass",
                "value": "3"
              },
              {
                "type": "totalSubOn",
                "value": "1"
              },
              {
                "type": "formationPlace",
                "value": "0"
              }
            ]
          },
          {
            "playerId": "6zuz6oyg26jxxyoneseblf4d1",
            "firstName": "Diego Francisco",
            "lastName": "Ávila Murillo",
            "shortFirstName": "Diego",
            "shortLastName": "Ávila",
            "matchName": "D. Ávila",
            "shirtNumber": 9,
            "position": "Substitute",
            "subPosition": "Attacker",
            "stat": [
              {
                "type": "formationPlace",
                "value": "0"
              }
            ]
          }
        ],
        "teamOfficial": [
          {
            "id": "al690owhged7e4z4q7ln3ecb9",
            "firstName": "Juan Carlos",
            "lastName": "León Zambrano",
            "shortFirstName": "Juan Carlos",
            "shortLastName": "León",
            "type": "manager"
          }
        ],
        "stat": [
          {
            "fh": "106",
            "sh": "57",
            "type": "accuratePass",
            "value": "163"
          },
          {
            "fh": "3",
            "sh": "1",
            "type": "blockedScoringAtt",
            "value": "4"
          },
          {
            "fh": "0",
            "sh": "1",
            "type": "cornerTaken",
            "value": "1"
          },
          {
            "fh": "3",
            "sh": "5",
            "type": "fkFoulLost",
            "value": "8"
          },
          {
            "fh": "7",
            "sh": "3",
            "type": "fkFoulWon",
            "value": "10"
          },
          {
            "fh": "1",
            "sh": "0",
            "type": "goalAssist",
            "value": "1"
          },
          {
            "fh": "4",
            "sh": "9",
            "type": "goalKicks",
            "value": "13"
          },
          {
            "fh": "1",
            "sh": "0",
            "type": "goals",
            "value": "1"
          },
          {
            "fh": "0",
            "sh": "1",
            "type": "goalsConceded",
            "value": "1"
          },
          {
            "fh": "1",
            "sh": "5",
            "type": "lostCorners",
            "value": "6"
          },
          {
            "fh": "4",
            "sh": "1",
            "type": "ontargetScoringAtt",
            "value": "5"
          },
          {
            "fh": "0",
            "sh": "1",
            "type": "penGoalsConceded",
            "value": "1"
          },
          {
            "fh": "0",
            "sh": "1",
            "type": "penaltyConceded",
            "value": "1"
          },
          {
            "fh": "0",
            "sh": "1",
            "type": "penaltyFaced",
            "value": "1"
          },
          {
            "fh": "37.9",
            "sh": "24.8",
            "type": "possessionPercentage",
            "value": "31.4"
          },
          {
            "fh": "2",
            "sh": "2",
            "type": "saves",
            "value": "4"
          },
          {
            "fh": "3",
            "sh": "1",
            "type": "shotOffTarget",
            "value": "4"
          },
          {
            "fh": "0",
            "sh": "5",
            "type": "subsMade",
            "value": "5"
          },
          {
            "fh": "9",
            "sh": "18",
            "type": "totalClearance",
            "value": "27"
          },
          {
            "fh": "1",
            "sh": "1",
            "type": "totalOffside",
            "value": "2"
          },
          {
            "fh": "151",
            "sh": "98",
            "type": "totalPass",
            "value": "249"
          },
          {
            "fh": "10",
            "sh": "3",
            "type": "totalScoringAtt",
            "value": "13"
          },
          {
            "fh": "10",
            "sh": "7",
            "type": "totalTackle",
            "value": "17"
          },
          {
            "fh": "10",
            "sh": "5",
            "type": "totalThrows",
            "value": "15"
          },
          {
            "fh": "1",
            "sh": "4",
            "type": "totalYellowCard",
            "value": "5"
          },
          {
            "fh": "0",
            "sh": "1",
            "type": "wonCorners",
            "value": "1"
          },
          {
            "fh": "9",
            "sh": "5",
            "type": "wonTackle",
            "value": "14"
          },
          {
            "type": "formationUsed",
            "value": "442"
          }
        ],
        "kit": {
          "id": "32483",
          "colour1": "#CC6600",
          "type": "home"
        }
      },
      {
        "contestantId": "85tqel61vdk8sfz1vsb1jykk7",
        "formationUsed": "4141",
        "player": [
          {
            "playerId": "ak80zcoqllp87ubfbrenem3f9",
            "firstName": "Rafael Enrique",
            "lastName": "Romo Pérez",
            "shortFirstName": "Rafael",
            "shortLastName": "Romo",
            "matchName": "R. Romo",
            "shirtNumber": 22,
            "position": "Goalkeeper",
            "positionSide": "Centre",
            "formationPlace": "1",
            "stat": [
              {
                "type": "accuratePass",
                "value": "19"
              },
              {
                "type": "gameStarted",
                "value": "1"
              },
              {
                "type": "goalKicks",
                "value": "3"
              },
              {
                "type": "goalsConceded",
                "value": "1"
              },
              {
                "type": "lostCorners",
                "value": "1"
              },
              {
                "type": "minsPlayed",
                "value": "90"
              },
              {
                "type": "saves",
                "value": "4"
              },
              {
                "type": "totalClearance",
                "value": "1"
              },
              {
                "type": "totalPass",
                "value": "23"
              },
              {
                "type": "formationPlace",
                "value": "1"
              }
            ]
          },
          {
            "playerId": "dp2tnjilpke1ph1fdjgno9zop",
            "firstName": "Eddy Joel",
            "lastName": "Mejía Montero",
            "shortFirstName": "Eddy",
            "shortLastName": "Mejía",
            "knownName": "Eddy Mejía",
            "matchName": "E. Mejía",
            "shirtNumber": 30,
            "position": "Defender",
            "positionSide": "Left",
            "formationPlace": "3",
            "stat": [
              {
                "type": "accuratePass",
                "value": "52"
              },
              {
                "type": "fouls",
                "value": "1"
              },
              {
                "type": "gameStarted",
                "value": "1"
              },
              {
                "type": "goalsConceded",
                "value": "1"
              },
              {
                "type": "minsPlayed",
                "value": "90"
              },
              {
                "type": "shotOffTarget",
                "value": "2"
              },
              {
                "type": "totalClearance",
                "value": "3"
              },
              {
                "type": "totalPass",
                "value": "56"
              },
              {
                "type": "totalScoringAtt",
                "value": "2"
              },
              {
                "type": "totalTackle",
                "value": "2"
              },
              {
                "type": "totalThrows",
                "value": "9"
              },
              {
                "type": "wasFouled",
                "value": "1"
              },
              {
                "type": "wonCorners",
                "value": "2"
              },
              {
                "type": "wonTackle",
                "value": "2"
              },
              {
                "type": "yellowCard",
                "value": "1"
              },
              {
                "type": "formationPlace",
                "value": "3"
              }
            ]
          },
          {
            "playerId": "eydla4uzkgvznobv6qm4njnit",
            "firstName": "Jhon Carlos",
            "lastName": "Chancellor Cedeño",
            "shortFirstName": "Jhon",
            "shortLastName": "Chancellor",
            "matchName": "J. Chancellor",
            "shirtNumber": 4,
            "position": "Defender",
            "positionSide": "Left/Centre",
            "formationPlace": "6",
            "stat": [
              {
                "type": "accuratePass",
                "value": "49"
              },
              {
                "type": "fouls",
                "value": "1"
              },
              {
                "type": "gameStarted",
                "value": "1"
              },
              {
                "type": "goalsConceded",
                "value": "1"
              },
              {
                "type": "minsPlayed",
                "value": "90"
              },
              {
                "type": "totalClearance",
                "value": "3"
              },
              {
                "type": "totalPass",
                "value": "50"
              },
              {
                "type": "wasFouled",
                "value": "1"
              },
              {
                "type": "formationPlace",
                "value": "6"
              }
            ]
          },
          {
            "playerId": "2irmtezvvd4kor9lb2i1ozv85",
            "firstName": "Luis David",
            "lastName": "Cangá Sánchez",
            "shortFirstName": "Luis",
            "shortLastName": "Cangá",
            "matchName": "L. Cangá",
            "shirtNumber": 33,
            "position": "Defender",
            "positionSide": "Centre/Right",
            "formationPlace": "5",
            "stat": [
              {
                "type": "accuratePass",
                "value": "54"
              },
              {
                "type": "gameStarted",
                "value": "1"
              },
              {
                "type": "goalsConceded",
                "value": "1"
              },
              {
                "type": "minsPlayed",
                "value": "90"
              },
              {
                "type": "totalClearance",
                "value": "1"
              },
              {
                "type": "totalPass",
                "value": "59"
              },
              {
                "type": "totalTackle",
                "value": "2"
              },
              {
                "type": "wasFouled",
                "value": "1"
              },
              {
                "type": "wonTackle",
                "value": "1"
              },
              {
                "type": "formationPlace",
                "value": "5"
              }
            ]
          },
          {
            "playerId": "b5b0gp63p5mdpusl6lc56q4bu",
            "firstName": "Gregori Alexander",
            "lastName": "Anangonó Minda",
            "shortFirstName": "Gregori",
            "shortLastName": "Anangonó",
            "matchName": "G. Anangonó",
            "shirtNumber": 29,
            "position": "Defender",
            "positionSide": "Right",
            "formationPlace": "2",
            "stat": [
              {
                "type": "accuratePass",
                "value": "23"
              },
              {
                "type": "fouls",
                "value": "3"
              },
              {
                "type": "gameStarted",
                "value": "1"
              },
              {
                "type": "goalsConceded",
                "value": "1"
              },
              {
                "type": "minsPlayed",
                "value": "76"
              },
              {
                "type": "totalPass",
                "value": "26"
              },
              {
                "type": "totalSubOff",
                "value": "1"
              },
              {
                "type": "totalTackle",
                "value": "2"
              },
              {
                "type": "totalThrows",
                "value": "4"
              },
              {
                "type": "wonTackle",
                "value": "2"
              },
              {
                "type": "yellowCard",
                "value": "1"
              },
              {
                "type": "formationPlace",
                "value": "2"
              }
            ]
          },
          {
            "playerId": "7f1eclcdjezvwn0vg4bm4muzu",
            "firstName": "Jerónimo",
            "lastName": "Cacciabue",
            "shortFirstName": "Jerónimo",
            "shortLastName": "Cacciabue",
            "matchName": "J. Cacciabue",
            "shirtNumber": 5,
            "position": "Defensive Midfielder",
            "positionSide": "Centre",
            "formationPlace": "4",
            "stat": [
              {
                "type": "accuratePass",
                "value": "72"
              },
              {
                "type": "fouls",
                "value": "1"
              },
              {
                "type": "gameStarted",
                "value": "1"
              },
              {
                "type": "goalsConceded",
                "value": "1"
              },
              {
                "type": "minsPlayed",
                "value": "89"
              },
              {
                "type": "totalPass",
                "value": "79"
              },
              {
                "type": "totalSubOff",
                "value": "1"
              },
              {
                "type": "totalTackle",
                "value": "2"
              },
              {
                "type": "totalThrows",
                "value": "1"
              },
              {
                "type": "wasFouled",
                "value": "1"
              },
              {
                "type": "wonTackle",
                "value": "1"
              },
              {
                "type": "formationPlace",
                "value": "4"
              }
            ]
          },
          {
            "playerId": "4xhrvnq03r13f2bwt0vxm46ol",
            "firstName": "Mauricio Sebastián",
            "lastName": "Alonso Pereda",
            "shortFirstName": "Mauricio",
            "shortLastName": "Alonso",
            "matchName": "M. Alonso",
            "shirtNumber": 32,
            "position": "Midfielder",
            "positionSide": "Left",
            "formationPlace": "11",
            "stat": [
              {
                "type": "accuratePass",
                "value": "23"
              },
              {
                "type": "fouls",
                "value": "2"
              },
              {
                "type": "gameStarted",
                "value": "1"
              },
              {
                "type": "goalsConceded",
                "value": "1"
              },
              {
                "type": "minsPlayed",
                "value": "76"
              },
              {
                "type": "shotOffTarget",
                "value": "1"
              },
              {
                "type": "totalClearance",
                "value": "1"
              },
              {
                "type": "totalOffside",
                "value": "1"
              },
              {
                "type": "totalPass",
                "value": "33"
              },
              {
                "type": "totalScoringAtt",
                "value": "1"
              },
              {
                "type": "totalSubOff",
                "value": "1"
              },
              {
                "type": "totalTackle",
                "value": "1"
              },
              {
                "type": "wonCorners",
                "value": "2"
              },
              {
                "type": "wonTackle",
                "value": "1"
              },
              {
                "type": "formationPlace",
                "value": "11"
              }
            ]
          },
          {
            "playerId": "d5hgq9en54sht3iy363fe2imt",
            "firstName": "Mauro Alberto",
            "lastName": "Díaz",
            "shortFirstName": "Mauro",
            "shortLastName": "Díaz",
            "knownName": "Mauro Díaz",
            "matchName": "M. Díaz",
            "shirtNumber": 28,
            "position": "Midfielder",
            "positionSide": "Left/Centre",
            "formationPlace": "10",
            "stat": [
              {
                "type": "accuratePass",
                "value": "52"
              },
              {
                "type": "cornerTaken",
                "value": "5"
              },
              {
                "type": "gameStarted",
                "value": "1"
              },
              {
                "type": "goalsConceded",
                "value": "1"
              },
              {
                "type": "minsPlayed",
                "value": "89"
              },
              {
                "type": "shotOffTarget",
                "value": "1"
              },
              {
                "type": "totalPass",
                "value": "71"
              },
              {
                "type": "totalScoringAtt",
                "value": "1"
              },
              {
                "type": "totalSubOff",
                "value": "1"
              },
              {
                "type": "totalThrows",
                "value": "1"
              },
              {
                "type": "formationPlace",
                "value": "10"
              }
            ]
          },
          {
            "playerId": "dbzannb5pw72n5t4sbotswhuy",
            "firstName": "Daniel Emiliano",
            "lastName": "Clavijo Romero",
            "shortFirstName": "Emiliano",
            "shortLastName": "Clavijo",
            "matchName": "E. Clavijo",
            "shirtNumber": 8,
            "position": "Midfielder",
            "positionSide": "Centre/Right",
            "formationPlace": "8",
            "captain": "yes",
            "stat": [
              {
                "type": "accuratePass",
                "value": "47"
              },
              {
                "type": "gameStarted",
                "value": "1"
              },
              {
                "type": "goalsConceded",
                "value": "1"
              },
              {
                "type": "minsPlayed",
                "value": "90"
              },
              {
                "type": "penaltyWon",
                "value": "1"
              },
              {
                "type": "shotOffTarget",
                "value": "2"
              },
              {
                "type": "totalClearance",
                "value": "1"
              },
              {
                "type": "totalPass",
                "value": "55"
              },
              {
                "type": "totalScoringAtt",
                "value": "2"
              },
              {
                "type": "wasFouled",
                "value": "2"
              },
              {
                "type": "yellowCard",
                "value": "1"
              },
              {
                "type": "formationPlace",
                "value": "8"
              }
            ]
          },
          {
            "playerId": "ecd9ao2y87pqxws6040ipn7dg",
            "firstName": "Azarías Emmanuel",
            "lastName": "Londoño González",
            "shortFirstName": "Azarías",
            "shortLastName": "Londoño",
            "matchName": "A. Londoño",
            "shirtNumber": 9,
            "position": "Midfielder",
            "positionSide": "Right",
            "formationPlace": "7",
            "stat": [
              {
                "type": "accuratePass",
                "value": "21"
              },
              {
                "type": "blockedScoringAtt",
                "value": "1"
              },
              {
                "type": "gameStarted",
                "value": "1"
              },
              {
                "type": "goals",
                "value": "1"
              },
              {
                "type": "goalsConceded",
                "value": "1"
              },
              {
                "type": "minsPlayed",
                "value": "90"
              },
              {
                "type": "ontargetScoringAtt",
                "value": "2"
              },
              {
                "type": "totalOffside",
                "value": "1"
              },
              {
                "type": "totalPass",
                "value": "29"
              },
              {
                "type": "totalScoringAtt",
                "value": "3"
              },
              {
                "type": "totalTackle",
                "value": "1"
              },
              {
                "type": "totalThrows",
                "value": "1"
              },
              {
                "type": "wonCorners",
                "value": "2"
              },
              {
                "type": "formationPlace",
                "value": "7"
              }
            ]
          },
          {
            "playerId": "6qdkaa9ae67qy7ipa11a8z17t",
            "firstName": "Byron Efraín",
            "lastName": "Palacios Vélez",
            "shortFirstName": "Byron",
            "shortLastName": "Palacios",
            "matchName": "B. Palacios",
            "shirtNumber": 18,
            "position": "Striker",
            "positionSide": "Centre",
            "formationPlace": "9",
            "stat": [
              {
                "type": "accuratePass",
                "value": "14"
              },
              {
                "type": "fouls",
                "value": "1"
              },
              {
                "type": "gameStarted",
                "value": "1"
              },
              {
                "type": "goalsConceded",
                "value": "1"
              },
              {
                "type": "minsPlayed",
                "value": "61"
              },
              {
                "type": "ontargetScoringAtt",
                "value": "3"
              },
              {
                "type": "totalOffside",
                "value": "2"
              },
              {
                "type": "totalPass",
                "value": "16"
              },
              {
                "type": "totalScoringAtt",
                "value": "3"
              },
              {
                "type": "totalSubOff",
                "value": "1"
              },
              {
                "type": "totalTackle",
                "value": "1"
              },
              {
                "type": "formationPlace",
                "value": "9"
              }
            ]
          },
          {
            "playerId": "9ggta4hzy0w4xkukczrti5y7e",
            "firstName": "José",
            "lastName": "Fajardo Nelson",
            "shortFirstName": "José",
            "shortLastName": "Fajardo",
            "matchName": "J. Fajardo",
            "shirtNumber": 7,
            "position": "Substitute",
            "subPosition": "Attacker",
            "stat": [
              {
                "type": "accuratePass",
                "value": "7"
              },
              {
                "type": "minsPlayed",
                "value": "29"
              },
              {
                "type": "ontargetScoringAtt",
                "value": "1"
              },
              {
                "type": "totalOffside",
                "value": "1"
              },
              {
                "type": "totalPass",
                "value": "8"
              },
              {
                "type": "totalScoringAtt",
                "value": "1"
              },
              {
                "type": "totalSubOn",
                "value": "1"
              },
              {
                "type": "totalTackle",
                "value": "1"
              },
              {
                "type": "wonTackle",
                "value": "1"
              },
              {
                "type": "formationPlace",
                "value": "0"
              }
            ]
          },
          {
            "playerId": "2uwx5yky9qc644tztx2zti28l",
            "firstName": "Facundo Martín",
            "lastName": "Martínez Montagnoli",
            "shortFirstName": "Facundo",
            "shortLastName": "Martínez",
            "matchName": "F. Martínez",
            "shirtNumber": 10,
            "position": "Substitute",
            "subPosition": "Midfielder",
            "stat": [
              {
                "type": "accuratePass",
                "value": "5"
              },
              {
                "type": "cornerTaken",
                "value": "1"
              },
              {
                "type": "minsPlayed",
                "value": "1"
              },
              {
                "type": "totalPass",
                "value": "5"
              },
              {
                "type": "totalSubOn",
                "value": "1"
              },
              {
                "type": "formationPlace",
                "value": "0"
              }
            ]
          },
          {
            "playerId": "425qrtm7ncs8qwstp9nrudxqs",
            "firstName": "Carlos Alejandro",
            "lastName": "Medina Castillo",
            "shortFirstName": "Carlos",
            "shortLastName": "Medina",
            "matchName": "C. Medina",
            "shirtNumber": 37,
            "position": "Substitute",
            "subPosition": "Defender",
            "stat": [
              {
                "type": "formationPlace",
                "value": "0"
              }
            ]
          },
          {
            "playerId": "eb2d87d8tfi6cxjcntkfdrdhw",
            "firstName": "Luis Johan",
            "lastName": "Moreno Zuñiga",
            "shortFirstName": "Luis",
            "shortLastName": "Moreno",
            "matchName": "L. Moreno",
            "shirtNumber": 15,
            "position": "Substitute",
            "subPosition": "Defender",
            "stat": [
              {
                "type": "accuratePass",
                "value": "6"
              },
              {
                "type": "fouls",
                "value": "1"
              },
              {
                "type": "minsPlayed",
                "value": "1"
              },
              {
                "type": "totalPass",
                "value": "8"
              },
              {
                "type": "totalSubOn",
                "value": "1"
              },
              {
                "type": "totalTackle",
                "value": "1"
              },
              {
                "type": "wonTackle",
                "value": "1"
              },
              {
                "type": "formationPlace",
                "value": "0"
              }
            ]
          },
          {
            "playerId": "c0wyvmrq61yzugvdt2qnneoes",
            "firstName": "Ignacio Ariel",
            "lastName": "Mosquera Arroyo",
            "shortFirstName": "Ignacio",
            "shortLastName": "Mosquera",
            "matchName": "A. Mosquera",
            "shirtNumber": 3,
            "position": "Substitute",
            "subPosition": "Defender",
            "stat": [
              {
                "type": "formationPlace",
                "value": "0"
              }
            ]
          },
          {
            "playerId": "dukia9yvlzkug4gw890nwneok",
            "firstName": "Alex Andrés",
            "lastName": "Rodríguez Reascos",
            "shortFirstName": "Álex",
            "shortLastName": "Rodríguez",
            "matchName": "A. Rodríguez",
            "shirtNumber": 23,
            "position": "Substitute",
            "subPosition": "Midfielder",
            "stat": [
              {
                "type": "accuratePass",
                "value": "9"
              },
              {
                "type": "minsPlayed",
                "value": "14"
              },
              {
                "type": "totalPass",
                "value": "11"
              },
              {
                "type": "totalSubOn",
                "value": "1"
              },
              {
                "type": "formationPlace",
                "value": "0"
              }
            ]
          },
          {
            "playerId": "ep0zxr95nch7d9gqbb47afg9g",
            "firstName": "Daykol Alejandro",
            "lastName": "Romero Padilla",
            "shortFirstName": "Daykol",
            "shortLastName": "Romero",
            "matchName": "D. Romero",
            "shirtNumber": 13,
            "position": "Substitute",
            "subPosition": "Defender",
            "stat": [
              {
                "type": "accuratePass",
                "value": "6"
              },
              {
                "type": "minsPlayed",
                "value": "14"
              },
              {
                "type": "shotOffTarget",
                "value": "1"
              },
              {
                "type": "totalPass",
                "value": "7"
              },
              {
                "type": "totalScoringAtt",
                "value": "1"
              },
              {
                "type": "totalSubOn",
                "value": "1"
              },
              {
                "type": "wasFouled",
                "value": "1"
              },
              {
                "type": "formationPlace",
                "value": "0"
              }
            ]
          },
          {
            "playerId": "1xwg0dqhh53zzuxben4gm7zmc",
            "firstName": "Isaac Mateo",
            "lastName": "Sánchez Cortez",
            "shortFirstName": "Isaac",
            "shortLastName": "Sánchez",
            "matchName": "I. Sánchez",
            "shirtNumber": 14,
            "position": "Substitute",
            "subPosition": "Attacker",
            "stat": [
              {
                "type": "formationPlace",
                "value": "0"
              }
            ]
          },
          {
            "playerId": "76301v2o43joyvf8jagpvf47o",
            "firstName": "Rooney Anderson",
            "lastName": "Troya Macías",
            "shortFirstName": "Rooney",
            "shortLastName": "Troya",
            "matchName": "R. Troya",
            "shirtNumber": 17,
            "position": "Substitute",
            "subPosition": "Midfielder",
            "stat": [
              {
                "type": "formationPlace",
                "value": "0"
              }
            ]
          },
          {
            "playerId": "qtilzeesr535rrklzb5d2qz8",
            "firstName": "Eric David",
            "lastName": "Valencia Reasco",
            "shortFirstName": "Eric",
            "shortLastName": "Valencia",
            "knownName": "Eric Valencia",
            "matchName": "Eric Valencia",
            "shirtNumber": 44,
            "position": "Substitute",
            "subPosition": "Defender",
            "stat": [
              {
                "type": "formationPlace",
                "value": "0"
              }
            ]
          },
          {
            "playerId": "chlj6ie4lu5ddamocsq58gh6",
            "firstName": "Elías Jair",
            "lastName": "Valencia Tenorio",
            "shortFirstName": "Elías",
            "shortLastName": "Valencia",
            "knownName": "Elías Valencia",
            "matchName": "E. Valencia",
            "shirtNumber": 1,
            "position": "Substitute",
            "subPosition": "Goalkeeper",
            "stat": [
              {
                "type": "formationPlace",
                "value": "0"
              }
            ]
          }
        ],
        "teamOfficial": [
          {
            "id": "a4otf91eol0vpjikp3lzkhus4",
            "firstName": "Diego Andrés",
            "lastName": "Martínez Carrera",
            "shortFirstName": "Diego",
            "shortLastName": "Martínez",
            "type": "manager"
          }
        ],
        "stat": [
          {
            "fh": "212",
            "sh": "247",
            "type": "accuratePass",
            "value": "459"
          },
          {
            "fh": "0",
            "sh": "1",
            "type": "blockedScoringAtt",
            "value": "1"
          },
          {
            "fh": "1",
            "sh": "5",
            "type": "cornerTaken",
            "value": "6"
          },
          {
            "fh": "7",
            "sh": "3",
            "type": "fkFoulLost",
            "value": "10"
          },
          {
            "fh": "3",
            "sh": "4",
            "type": "fkFoulWon",
            "value": "7"
          },
          {
            "fh": "3",
            "sh": "0",
            "type": "goalKicks",
            "value": "3"
          },
          {
            "fh": "0",
            "sh": "1",
            "type": "goals",
            "value": "1"
          },
          {
            "fh": "1",
            "sh": "0",
            "type": "goalsConceded",
            "value": "1"
          },
          {
            "fh": "0",
            "sh": "1",
            "type": "lostCorners",
            "value": "1"
          },
          {
            "fh": "2",
            "sh": "4",
            "type": "ontargetScoringAtt",
            "value": "6"
          },
          {
            "fh": "0",
            "sh": "1",
            "type": "penaltyWon",
            "value": "1"
          },
          {
            "fh": "62.1",
            "sh": "75.2",
            "type": "possessionPercentage",
            "value": "68.6"
          },
          {
            "fh": "3",
            "sh": "1",
            "type": "saves",
            "value": "4"
          },
          {
            "fh": "3",
            "sh": "4",
            "type": "shotOffTarget",
            "value": "7"
          },
          {
            "fh": "0",
            "sh": "5",
            "type": "subsMade",
            "value": "5"
          },
          {
            "fh": "3",
            "sh": "7",
            "type": "totalClearance",
            "value": "10"
          },
          {
            "fh": "3",
            "sh": "2",
            "type": "totalOffside",
            "value": "5"
          },
          {
            "fh": "247",
            "sh": "289",
            "type": "totalPass",
            "value": "536"
          },
          {
            "fh": "5",
            "sh": "9",
            "type": "totalScoringAtt",
            "value": "14"
          },
          {
            "fh": "7",
            "sh": "6",
            "type": "totalTackle",
            "value": "13"
          },
          {
            "fh": "11",
            "sh": "5",
            "type": "totalThrows",
            "value": "16"
          },
          {
            "fh": "1",
            "sh": "2",
            "type": "totalYellowCard",
            "value": "3"
          },
          {
            "fh": "1",
            "sh": "5",
            "type": "wonCorners",
            "value": "6"
          },
          {
            "fh": "4",
            "sh": "5",
            "type": "wonTackle",
            "value": "9"
          },
          {
            "type": "formationUsed",
            "value": "4141"
          }
        ],
        "kit": {
          "id": "29251",
          "colour1": "#0033FF",
          "type": "away"
        }
      }
    ],
    "matchDetailsExtra": {
      "matchOfficial": [
        {
          "id": "5poth872uazogjp4p1x93hzpw",
          "type": "Main",
          "firstName": "Russell Macario",
          "lastName": "Teran Leon",
          "shortFirstName": "Russell Macario",
          "shortLastName": "Teran Leon"
        },
        {
          "id": "cmxw6n89rwqtf99k5dhdhlko9",
          "type": "Assistant referee 1",
          "firstName": "David Alberto",
          "lastName": "Vacacela García",
          "shortFirstName": "David",
          "shortLastName": "Vacacela"
        },
        {
          "id": "6jnl3l5yl0okyyd7i7fpkx61h",
          "type": "Assistant referee 2",
          "firstName": "Luis Hedison",
          "lastName": "González Cordero",
          "shortFirstName": "Luis Hedison",
          "shortLastName": "González Cordero"
        },
        {
          "id": "9shpiy04dncdglzf4sbpe8ine",
          "type": "Fourth official",
          "firstName": "Henri",
          "lastName": "Arizaga",
          "shortFirstName": "Henri",
          "shortLastName": "Arizaga"
        },
        {
          "id": "7v22ujcpnhe7qin2jmp0zazf9",
          "type": "Video Assistant Referee",
          "firstName": "Franklin Andrés",
          "lastName": "Congo Viteri",
          "shortFirstName": "Franklin",
          "shortLastName": "Congo"
        },
        {
          "id": "3i21r4g7vn4vndv92clu4bz3e",
          "type": "Assistant VAR Official",
          "firstName": "Adrián",
          "lastName": "Lescano",
          "shortFirstName": "Adrián",
          "shortLastName": "Lescano"
        }
      ]
    }
  }
}